starlette_compress/__init__.py
starlette_compress/_brotli.py
starlette_compress/_gzip.py
starlette_compress/_identity.py
starlette_compress/_utils.py
starlette_compress/_zstd.py
starlette_compress/_zstd_legacy.py
starlette_compress/py.typed
starlette_compress-1.7.0.dist-info/METADATA
starlette_compress-1.7.0.dist-info/WHEEL
starlette_compress-1.7.0.dist-info/RECORD
