Metadata-Version: 2.4
Name: starlette-compress
Version: 1.7.0
Summary: Compression middleware for Starlette - supporting ZStd, Brotli, and GZip
Project-URL: Issues, https://github.com/Zaczero/pkgs/issues
Project-URL: Repository, https://github.com/Zaczero/pkgs/tree/main/starlette-compress
Author-email: Kamil Monicz <kamil@monicz.dev>
License-Expression: 0BSD
Keywords: asgi,brotli,compression,deflate,encoding,fastapi,gzip,http,middleware,performance,response,starlette,web,zstandard,zstd
Classifier: Development Status :: 5 - Production/Stable
Classifier: Environment :: Web Environment
Classifier: Framework :: AnyIO
Classifier: Framework :: AsyncIO
Classifier: Framework :: FastAPI
Classifier: Framework :: Trio
Classifier: Intended Audience :: Developers
Classifier: License :: OSI Approved :: Zero-Clause BSD (0BSD)
Classifier: Operating System :: OS Independent
Classifier: Programming Language :: Python :: 3.9
Classifier: Programming Language :: Python :: 3.10
Classifier: Programming Language :: Python :: 3.11
Classifier: Programming Language :: Python :: 3.12
Classifier: Programming Language :: Python :: 3.13
Classifier: Programming Language :: Python :: 3.14
Classifier: Topic :: Internet :: WWW/HTTP :: Dynamic Content
Classifier: Topic :: Internet :: WWW/HTTP :: WSGI :: Middleware
Classifier: Topic :: Software Development :: Libraries :: Python Modules
Classifier: Typing :: Typed
Requires-Python: >=3.9
Requires-Dist: brotli>=1; platform_python_implementation == 'CPython'
Requires-Dist: brotlicffi>=1; platform_python_implementation != 'CPython'
Requires-Dist: starlette
Requires-Dist: zstandard>=0.15; python_version < '3.14'
